{"info": {"description": "COCO 2018 Panoptic Dataset", "url": "http://cocodataset.org", "version": "1.0", "year": 2018, "contributor": "https://arxiv.org/abs/1801.00868", "date_created": "2018-06-01 00:00:00.0"}, "licenses": [{"url": "http://creativecommons.org/licenses/by-nc-sa/2.0/", "id": 1, "name": "Attribution-NonCommercial-ShareAlike License"}, {"url": "http://creativecommons.org/licenses/by-nc/2.0/", "id": 2, "name": "Attribution-NonCommercial License"}, {"url": "http://creativecommons.org/licenses/by-nc-nd/2.0/", "id": 3, "name": "Attribution-NonCommercial-NoDerivs License"}, {"url": "http://creativecommons.org/licenses/by/2.0/", "id": 4, "name": "Attribution License"}, {"url": "http://creativecommons.org/licenses/by-sa/2.0/", "id": 5, "name": "Attribution-ShareAlike License"}, {"url": "http://creativecommons.org/licenses/by-nd/2.0/", "id": 6, "name": "Attribution-NoDerivs License"}, {"url": "http://flickr.com/commons/usage/", "id": 7, "name": "No known copyright restrictions"}, {"url": "http://www.usa.gov/copyright.shtml", "id": 8, "name": "United States Government Work"}], "images": [{"license": 2, "file_name": "000000142238.jpg", "coco_url": "http://images.cocodataset.org/val2017/000000142238.jpg", "height": 427, "width": 640, "date_captured": "2013-11-20 16:47:35", "flickr_url": "http://farm5.staticflickr.com/4028/5079131149_dde584ed79_z.jpg", "id": 142238}, {"license": 1, "file_name": "000000439180.jpg", "coco_url": "http://images.cocodataset.org/val2017/000000439180.jpg", "height": 360, "width": 640, "date_captured": "2013-11-19 01:25:39", "flickr_url": "http://farm3.staticflickr.com/2831/9275116980_1d9b986e3b_z.jpg", "id": 439180}], "annotations": [{"segmentation": {"counts": "eme31V=8H8H7I4L4L5M2NDQD^Oo;b0<1N101XOSOQEn0P;XOgDj0Y;^O^Dd0a;b010iN`NlEN8d1d9iNoEI6a12dNo8c0hFm1T9U1O100O100O10000000^OWGbLh8[3]GdLc8Y3aGfL_8V3gGhLY8V3i04K52N2N2RNUF9n9FUF6m9IVF2m9MVFNm:QOVE=F@T<<a0L4K9HjoP4", "size": [427, 640]}, "area": 3528, "iscrowd": 0, "image_id": 142238, "bbox": [282, 207, 48, 149], "category_id": 1, "id": 0}, {"segmentation": {"counts": "[__51X=4L3N2M2N2N2J6J6M3gLZOkIh0S6\\OTGE_2P1\\6\\OTGE^2e0cM_Ok88RGE^2d0hM^Oh8a0]H_O]Oa0B]Oc8f0YHB]O;J\\O_8P1nG_OA:4VO]8U1fGf0o8@hFb0Y9f12M2NXObL_Ge3c8\\LYGf3g8]LVGd3j8]LSGd3S97hGULQ7j3nHYLR7d3mH`LT7]3dHmLa8n1YGXNg8h1WGZNh8i1TGYNl8i1PGYNl8m1PGUNm8k2UGVLh8j3\\GUL`8a0]G`25oLi7L]Hf0R1S1iN[Nh7MYHf0\\1k0gNaNd7OUHe0g1d0cNhNa71PHd0Q2=bNmN]7m0WJO_NTOZ7k0]JI^N[OU7i0eJFXN@S7d0PH[Om2:QNGS7?`L@b3:l4InSW2", "size": [427, 640]}, "area": 3751, "iscrowd": 0, "image_id": 142238, "bbox": [420, 183, 49, 173], "category_id": 1, "id": 1}, {"segmentation": {"counts": "jWa32X=2N2N2N2N1O2M3N2N2^N_OWFb0f9DVF>f9HVF:f9LVF5g90UF3U8VO]Hm0ZOZO[O6m8D]HP1WOUOD4h8OSHn0\\OoNN1a85QHQ1XOkN<K[8;nGb1LoMU8b0kG`1Q9bNkF^1W9eNcF]1^9fN\\F[1f9iNTFX1m9P14K4iNiEUO]:g0gEjNg:S1\\EnNd:o0_EPOd:j0`EVOb:d0aE\\Ob:>bEB`::bEE_:8cEI^:3eEM[:0hEOY:OhE2X:KkE4V:ImE9Q:FoE=P:AQF>o9CQF;Q:DoE;R:EoE9S:GlE9U:FkE9e;N1O2O0L5LdbS4", "size": [427, 640]}, "area": 2301, "iscrowd": 0, "image_id": 142238, "bbox": [271, 118, 53, 141], "category_id": 1, "id": 2}, {"segmentation": {"counts": "og\\46P=8G9K5L3L5L5J5L5N1O2N1N4M7G9G9H7H2N3M2O1N3M2N3M2O2M2bFfLg8\\3mFnLT9e3O000001O01O01O0000007Jg0XO`0@6I7nMeEg0c;L3M4L4L3L3M3N3L3M3NS`W3", "size": [427, 640]}, "area": 4076, "iscrowd": 0, "image_id": 142238, "bbox": [337, 208, 54, 149], "category_id": 1, "id": 3}, {"segmentation": {"counts": "Tnc02V=3J6K6J5J7J5J6aNZORFn0e9FgEb0U:]1L3UOUMSGo2k8SMQGP3n8RMPGo2o8SMPGn2n8TMQGZ2NbMP96PGT26eMj8o2[GoLf8m2_GRMa8l2bGRM_8k2eGTM[8j2hGTMY8j2jGUMV8i2mGUMU8h2nGWMR8g2QHWMP8g2SHXMm7f2]1O1O1O1N7H:nM\\Ek0h;HYPX7", "size": [427, 640]}, "area": 2931, "iscrowd": 0, "image_id": 142238, "bbox": [47, 221, 36, 138], "category_id": 1, "id": 4}, {"segmentation": {"counts": "ine52U=4L4O1O6K2M3@^OSDf0f;_OXDe0c;^O[Dg0`;^O[Dd0b;f0M0O2OU1jN11N2O0L5L4L5JnEgMe9Y1fEROf0a0m8:^FPOg0i0k86_FmNf0Q1k80bFjNd0Y1j8L]G6c8J[G9d8GYG=f8CTGlNZOd1a9APGoN_Oa1a9AiFROG^1_9BcFUONZ1^94cFL^93jGfNV8Y1PHbNQ82cFg0_1SOn76iF>\\1\\Ok76oF6W1Cm76ZIHh68XIEl6:SIEP7:PIDR7;Q3O1N01OO00000010O0001O00001O00LJTC6l<41O01O01O2O0O102M4LVgg1", "size": [427, 640]}, "area": 2969, "iscrowd": 0, "image_id": 142238, "bbox": [436, 125, 70, 151], "category_id": 1, "id": 5}, {"segmentation": {"counts": "jfT31Y=2N2N2N2N2N2O1N3N1O1hF^Od5d0YJ_Of5h0RJZOm5i0nIZOQ6h0kIZOU6i0PI0o63fGPO8o0S8OdGYO1k0[8JcGCKe0c8FPGTO9h0Kb0l8APGYO3]2n8XNoFX2Q9gMnFl11cMS9V3SGhLg8Z3_GdL]8\\3jGaLT8]3RHaLl7]3ZHbLc7]3`GeL\\9Z3eFmL>FR8[1]Gb02dN6DZ8V1`G?OnNMCb8Q1dG;LA_84fGg1m7PMSHm0LVO7l2k7VNUHiN1Q3j7TNfHk1Y7SNkHm1T7PNPIo1o6oMeI`1c6UNaIZ1ZN[NV87dIV1`N`No74fI7QN1h0@d72gI9UNDS<4b[c4", "size": [427, 640]}, "area": 3557, "iscrowd": 0, "image_id": 142238, "bbox": [241, 183, 45, 171], "category_id": 1, "id": 6}, {"segmentation": {"counts": "aoQ82X=3M2N2N1O2N1O0000000O1N2O001O1N2O1fCAe;c0VDKZ;Y1K4N3VH", "size": [427, 640]}, "area": 477, "iscrowd": 0, "image_id": 142238, "bbox": [618, 248, 22, 68], "category_id": 1, "id": 7}, {"segmentation": {"counts": "XVT6f0d<2O1M3O11O2N101N1O2N1OO100O010O0`DAU:?dEJY:6_E5_:KXE`0e:@oDn0o:j0M3M2M3N3L3N3L3M3M4M1N3M3N2M3M;E10001O01O0010OhLcGb1^8\\NkG\\1U8bNTHW1m7gNWHV1j7gNZHX1g7eN]HX1f7cN^H[1e7aN_H\\1j9N3M4L3M4L3M4L3M5K5J7HoX\\1", "size": [427, 640]}, "area": 3968, "iscrowd": 0, "image_id": 142238, "bbox": [470, 211, 63, 142], "category_id": 1, "id": 8}, {"segmentation": {"counts": "b7\\1P<VOi001O1O1O4L2N3LokV8", "size": [427, 640]}, "area": 153, "iscrowd": 0, "image_id": 142238, "bbox": [0, 242, 9, 44], "category_id": 1, "id": 9}, {"segmentation": {"counts": "XTP22X=2M3N2N3ZNGTF<c9NZF4R8BkGc0ONT8E`Gh08EV8IVGk0`0_OY8JkFQ1i0WOZ8d1aG_N]8d1`G^N_8d1]G_Na8d1\\G\\Ne8g1VGZNj8i1SGWNm8l1oFUNR9R3O1000APGbLR9[3YG\\Lg8b3b0O1N3M2N2O1N3M2cMQF]1P:_NXF[1Q;J5jNdD5^;FjDEI4^;7U1000000O2O000000000O101O0000000O10001O002NTdb5", "size": [427, 640]}, "area": 3330, "iscrowd": 0, "image_id": 142238, "bbox": [153, 217, 58, 140], "category_id": 1, "id": 10}, {"segmentation": {"counts": "kbd7<n<5L:B8I3010J6I8L28I0O02_OnCFhWa0", "size": [427, 640]}, "area": 355, "iscrowd": 0, "image_id": 142238, "bbox": [586, 229, 13, 39], "category_id": 1, "id": 11}, {"segmentation": {"counts": "Sg`32X=2N2N1O1O2O0WDI]:9`EI_:8^EJb:8[EHf:;QEKo::fDL[;P12O0O1O2N1O:F4L4M3L4L5K5J7JdY_4", "size": [427, 640]}, "area": 636, "iscrowd": 0, "image_id": 142238, "bbox": [270, 124, 26, 61], "category_id": 1, "id": 12}, {"segmentation": {"counts": "[co08Q=4M2M3N2M3N2N1O2N1K5L4PM7QH6m7N\\GkNHZ1j8NZGlNFZ1o8MWGf0h8o10000O100000O100O1O1O1O2M2N3K5N2N3M3Nc0\\O4L4L`0_O2N2O1N2O1O1O1N3gNjD9X;GW1N2N2N3L4Le]l06UbSO4H7D<`N]OkEo0T:SOhEP1W:ROdEQ1h8cNXH>mNR1h8dNYH;mNR1i8eNYH:kNS1k8fNXHU2g7mMlG^OBe2a8VNdGWOJc2b8ZN_GTONc2b8iN^GW1b8oNXGQ1h8i1000000000000000O2O0O2N2N2N3M2XOWGjLm8S3h0M2N3L>B2M3N2`NSE`0o:@XEWOKi0o:0_EMb:3`EIc:6_EFc::_EBc:>U100O1O1O1O1O1O10000001O02N2N3M3M00O1OCYC8e<I_C4`<L?Oag=4YXB5_Oa0O01M2O2O0O3N2MaMInG5P8OPHNP84b22N2O1N3aC]OR<c0oCBk;?TDF23k:7TE`0k:ATE?l:BSE>m:Q1O0[EhMW:Y2gEhMV1Ob7X2VGkMW10a7V2TGmMY11b7Q2QGRN\\10O3h5h2gIXM<5k5]3oH`Le0d0[6_3aIdL]6_3_IdL`6^3[ImL\\6S5cI^Im5c6oIaIQ6m6O10000000kKRJk0n5POZJn0e5lNdJQ1\\5mNiJhMXOf2m5CnJcM@a2a5KTK^M_Of2\\5LnK3P4MUL`MRNV2g5;nLYOQ3j0oLTOo2?YJSNW3l0`2P1]JSNT3k0^2Q1bJTNP3h0^2S1^NjNb14ZJQOQ5f0e0:JA5`0L^O5b0L\\O4e0NXO3h0OTO3l01nN1R1T600TORD;n;CVD;j;DXD:i;EYD:g;E[D9f;CoCL<`0f;C^D<c;E\\D:f;EZD:g;GXD8i;IVD5l;LRD3P<MPD0T<0jC0W<2gCL\\<5_CLd<<2M4LWGHe44XK8cNFX7f0`H^OZ7h0\\F]O3F4Lj0<]8]1aF]N22l06_8S2]GoM`8U2]GmMb8V2ZGlMd8V2YGlMf8V2WGmMh8U2TGmMl8T2RGmMn8T2oFnMP9U2lFmMS9V3O1O1C=M3O1N110O00101O0O2N1O100O1000000000000000VOkG^LU8`3mG`LT8]3oGaLR8_3nGaLS8_3mG_LU8a3kG]LW8c3iG[LZ81_GQ39jL\\81]GS3;hLj8U3h0M3I6J6M3N3N1NTF_MR9_2mFdMU9Y1WF]Oc0\\OX9R1[FVOFGg02a9e0XF_O=N_9;aGEf82[GOo:1O1N1O1mYe1OceZNHPD<n;MiC5Q<e0O1N2O1O2O4L1O1O001O0001eNeDc0];[OhDa0[<E5K1M4KXhc0", "size": [427, 640]}, "area": 24295, "iscrowd": 1, "image_id": 142238, "bbox": [75, 111, 517, 262], "category_id": 1, "id": 13}, {"segmentation": {"counts": "fWf42W=4M2N2N2KEWC<h<41O001O1O1N101N3N2Knn]3", "size": [427, 640]}, "area": 175, "iscrowd": 0, "image_id": 142238, "bbox": [360, 116, 16, 17], "category_id": 37, "id": 14}, {"segmentation": {"counts": "0b7i51O001O1O1O2N4L2N00000000000000N2N2M3N200O100000000O1O11O0000O1001O7YJWH^5n7cJUHT5Q801O0000O1001O00000000O1001O0000001O0000M3L4M3UOoJYIT5f6nJVIU5i6mJUIT5j6nJUIR5j6PKUIP5j6RKTIo4l6h00000000000001O000000000000003M6ZJQId4k70O1000000kNU1N2O1O1O10000O100000000000000001O001O1O1O2N2Nc0]O3M3M;ELiJRH00W5n7400000000O100000000001O0000O11O00O1O1N2O1JaJ^Ha5b7400O1N200000000000YJaHb5a7\\J_Hd5d702N1O2N2N2N1O00O100O100SOfJiIZ5V6lJeIT5Z6RKaIn4_6VKUIR5j6h0O100O100O1O100O100001O0000001O0000001O0\\JVIg4j6UK^Ig4c6TKaIl4_70000000000000000000000000000000SOjJeIV5Y6nJdIS5[6oJcIR5\\6QKbIo4]6SKaIn4^6[KYIf4g6o0O1000000000000000000001O001O1O1O2N1O2N2N1O2N<D0000000000001O00[OZJeIf5Z6\\JeId5Z6^JeIb5Z6`JeI`5Z6bJeI^5Z6dJeI\\5Z6fJeIZ5[6hJcIX5\\6jJcIV5]6kJbIU5^6lJaIT5^6nJaIR5_6UKZIk4f6m00000001O001O001O002NJ6L4N2N2N2mMSIfMo6Y2SIeMn6Z2TIdMm6[2TIcMn6\\2TIbMm6]2TIVMJnNS7l3TISMT1oNa4m3\\JRMR1XO^4e3aJPMQ1\\O`4c3aJnLn0Ab4`3cJfLL[Od0a0n4]3gJ\\LMJ_OMd0b0Z5[3dKTLWOc0V5Y3aKSLYOf0W5V3_KSLZOi0X5S3[LlLg3P3mIXL\\2g0h3P3_LmLb3S3bLhL`MBc5e3RMaL^MJa5e3dM\\L]2c3cM]L^2c3e3000000001O001O001O3M2N3M3M2NHTGSLj8k3<O1O1O100O100000000000000001O001O00001O001O00001O001O1O1O1O000000N2O1O1N2N2O1NjH[Lj4d3UK`Li4_3VKeLh4Z3WKYMX4f2fJ_LQOd1Y6l1gJ^NY5a1hJ`NW5`1iJ`NW5_1jJaNV5_1jJaNV5_1jJbNU5^1kJbNU5^1kJbNU5^1kJbNU5^1kJbNU5^1jJdNU5\\1kJdNU5\\1jJeNV5[1iJgNV5Y1iJhNW5X1hJiNX5X1fJiNZ5W1eJkNZ5U1dJmN\\5S1bJoN^5Q1_JSO`5n0^JSOb5m0\\JUOd5l0YJVOg5k0WJWOh5j0UJMV55fJ>i4DSK9R5k35M3L4O1N200O1O1000000O1O1O1O1C=M3O1N200O1O10000O1O1O100O10000000000000000001O001O1O1O2kIYIb5i6ZJYIf5W7O1O1O0000_O[J\\Ie5b6_J[Ib5d6_J[Ib5e6_JYIb5g6a0O1UN_IkLb6Q3cInL]6n2gIRMY6m2hISMX6[NgIT46]M`6_NQIR1:^17nN_6aNQIR1:^19RN\\OL^7d0nHo0FXNf04ZOL_7j0nHh0H\\Ne00XO0_7I]HP1?j0K[Ng0LTO3d7l0gHi0OWNd00Q7P1[Hi0^9WObFi0^9WOcFg0^9YOcFf0]9ZOcFe0_9[OaFTO^O[1o9BcFSO^O\\1o9@dFSO]O]1n9AjF`0T9AlFoNYO]1j9DQG>l8BXG>e8AZGl0[8SOfGn0Y8QOhGP1W8oNlGP1S8POmGP1S8QOnGm0S8QOPHm0P8TOPHk0P8UOPHl0o7UOQHj0o7VOSHh0m7YOSHg0l7ZOTHf0[1gN\\3a0YKj0VOYNa1<o3a0\\KROfNc1=cN]18W4;_Kj0mNiNW11e44XKS1kNC=VO_54XKU1lNB<VO^53YKX1lNA<SO_53YKZ1lNA;RO`52VK`1nN^O:POa51XKc1kN_O:mNb52ZKb1iN@:kNc53ZKb1iN@;iNc54ZKc1hNA;gNc55YKc1iNB<fNa56[K_1hNG;dNb56VKAgNl16J<bNa57dJBYON53Ik18J;aNa58eJAXOO6R21F<\\Nc5<aJ@[O14o11J;UNi5a0SJ_OA040L66k11Kk6eNXI_OG1OO31M57i10Nk6dNXI_OF2OO23O30I2n150i7YNRHL03ML2l151k7XNPHLNM1;Oc171l7YNmGN051^1OYN7n1m7g0WHYOl7e0SH\\Om7c0TH\\Om7c0SH]Om7d0RH\\On7f0QHZOm7h0RHXOP8g0PHXOR8i0kGXOV8j0fGVO[8l21O10DUKSH0Lm4l7TKSH24m4i7XKTHj4k7;O2L3QIiJj5X5TJiJk5X5TJiJl5X5QJjJo5W5oIjJQ6X5kIjJW6V5fIkJZ6X5aIjJ\\6\\O`Im50hJ`6[O`Ie6`63N20000O1M30000000KfIWI\\6f660ON_I\\Ib6c6^I]Ia6d6_I[Ib6e620000O10O101O001]IYI`6j6O0N30O0UIdIg6`60001O00O12NNM_I`I^6c64100GZIiIOOh6W6YIkIONh6T6YIkIP7U63O10000O11ONERJ]Io5a6=L5O1N102N2OO100000eIVIU6k6jIUIV6k6jIUIV6m6gITIZ6n61L;GM5L4O2ONdIVIY6o62M0010O02`IfIk5o6N03M01N12N2NO01N2O1O1O10001N1OL[IdId6]6^IaIb6_6500aIZIZ6j6104J03OOdIVIW6Q7M3M2M3M3O1N21O1O01O0000O1J6M3O]O", "size": [427, 640]}, "area": 130762, "iscrowd": 0, "image_id": 142238, "bbox": [0, 0, 640, 263], "category_id": 184, "id": 15}, {"segmentation": {"counts": "Z_g5;n<2TCER1:V:1gDFR1:W:4iEMV:2kE1R:OkDBP1?U:2kEOT:1lENU:2kENU:2kEOT:1lE0S:0mE0S:1mEOTO^Oh:b0UF0SO^Oh:c0TF0SO]Oi:b0UF6k9IVF7oNYOg:`0ZF;f9DZF`0c9@\\F?f9AYF`0g9@XFa0h9_OWFd0g9\\OYFd0g9\\OZFe0d9\\OZFg0d9YO]Fg0b9YO^Fg0b9YO_Fg0`9YO`Fi0^9WOcFi0\\9WOeFi0Z9XOdFh0]9XOcFj0ROfNT:e0eFk0Z9]O^Fd0a9\\O_Fc0b9]O^Fb0c9_O\\Fa0d9@[F=h9CWF>i9BXF?f9AZF?f9AYF`0g9@YF?h9AYF`0e9@[F;AgNS:n0\\FIBYON53IR:o0\\FJAXOO6Z:h0VFI@[O14X:h0WF@_OA040L66T:i0WF[O_OG1OO31M57S:h0XF[O_OF2OO23O30I2Y:k1nEUNL03ML2W:m1nESNLNM1;Oo9o1nEQNN051o9o1o02N0000O1O1N21O1O1O000000DhD`N0LZ;_1gD`N24Z;\\1kDaNV;_1;O1M300O10000002N00MUDfNk;Z1UDfNk;Z13N20000O1M3000000000000O11OO10000000000O10000000000N21O0iCPOS<T10001O00O12NN2M3O100GiCZOOOY<f0hC\\OONY<c0hC\\Oa<d03O10000O11ON21OO10000O11O1OO100000\\C_O^<b0aC^O_<b0aC^O_<d0^C]Ob<f00M3O11O1O2NO_C[O^<j0O00001O0000003M00O12N2NO10000000000001O00KjCUOV<k0lCSOT<m05001O004LN200N2N2N2M3M3O1N21O1O00000000000000", "size": [427, 640]}, "area": 8204, "iscrowd": 0, "image_id": 142238, "bbox": [440, 0, 200, 103], "category_id": 187, "id": 16}, {"segmentation": {"counts": "n8]4U8dKZHe4f7`00000000000IkJYHT5g7oJSHT5m750000000000N2N2M3N200O100000000O1O11O0000O1001O7YJWH^5n7cJUHT5Q801O0000O1001O00000000OeMmG@S8=PHCQ86VHIj72[HNe7MaH2_7HgH8Z7BkH>U7\\ORIc0n6nM[Ha0n0a1j7kM_HT2\\90001O001O0000\\OPNmEP2o9UNPFk1k9[NSFf1j9^NUFb1i9aNUF`1i9cNVF]1h9fNVF[1h9hNWFX1g9kNWFV1g9mNXFS1e9QOYFP1e9cNbFe1]9ZNgFd1X9\\NjFc1U9\\NnFc1Q9]NQGb1m8^NVGa1]7fMUIl0@]1[7kMmHk0IZ1Y7QNeHh04V1W7KjH5V7FoH:Q7BSI>T7nNYIR1i6WNPHHZ1P2h6TNRHFZ1V2f6PNmIP2g800000000000O100O1O1O1O1N2N2L4O1O1O100O1O1O1cMYMTJi2h5TMRH003T2k2j5YMUJh2k5XMSJj2m5VMRJk2n5UMQJl2o5TMPJm2o5TMoIn2Q6SMfHO9P3Q7QMfHU4Z7lKdHU4\\7lKbHU4^7lK`HU4a7lK[HV4e7lKWHV4i7f0O11O00O1O1N2O1JaJ^Ha5b7400O1N200000000000YJaHb5a7\\J_Hd5d702N1O2N2N2XMSHNn70UHNk70XHOg71[HNe71]HNb7_NUHa0<o0_7XN_Hf04Q1]7RNhHi0NT1Z7kMSIm0EW1b8eNaGZ1a8cNaG\\1b8_NaG`1a8]NaGb1a8ZNbGe1`8XNaGh1b8SN_Gn1c8oM]GR2e8jM\\GW2k91000000AnMeER2Y:a0N2O1N2N2N2O1N2N2kMhLUJZ3k5jLPJW3P6mLmHH2]3Q7kLcH5GE6]3`7iLcH8AM2T3j7gLcH\\4]7dKbH]4^7cKbH]4^7cKbH]4^7dKaH\\4_7dKaH\\4_7dKaHg1N8a7QN`Hf137]7SN`H`1:<V7TN`HU1f0f0j6UNPI:b0`1^6WNQI5d0c1[6XNSI0e0h1X6XNTIMg0j1T6ZNVIJg0l1R6[NXIFh0o1P6[NVKe1i4[NXKe1g4[NZKe1g4YNZKg1U80000000000000000000O100O1O1O1O1O1YOWNjEk1U:f0O1O1N2N2M3N2`NfLmH\\3S7kLdGKi0\\3c7RMZHo2f7SMVHo2j7SMRHo2n7SMnGo2R8U100O1O1O1O1O1O100000aMgGLZ81iGNW81kGNU80nGOR8OQH0o7XOiHh0W7PNlGe0o0[1U7nMSH?k0c1R7kM[H;e0j1P7iMbH4b0S2b90001O_OmMjES2R:SNlEm1P:YNnEg1n9_NPFa1l9eNRF[1k9iMVFk0M\\1X:[NhEi1\\:nMjEQ2Z:eMlE[2b:000000000000000EeMfE[2[:fMcEZ2g:01O3M1O00000000BoM`ES2^:>O1N2N2O1N2N2O1N2OWMXFQ2e:L1O0000000000000000_OSNdEm1X:XNgEh1V:\\NiEd1T:aNjE_1R:fNmEZ1Q:Q1N2N2N2N2N2M3;E2N2N2N2N9G2_MbEQ2_:kMeET2j:O1O1O1O1O001O00hLRNSKn1k4]NlJc1R5`NmJ`1S5aNlJ_1V5bNWH@V2n1g5TOmIl0V6SOhIm0\\6@RIa0Q7^OmHb0X7[OeHf0d7SOYHn0P8mNkGT1^8hN]GX1k8aNSG`1o8_NoFb1T9]NiFd1Y9\\NcFf1_9\\N[Ff1h9m02N3M2N3M2^MkEj1W:jMSFV2a:000001O000000001O00000000006J3M2N1O1O1O1O001O00000000000000000000O100O1001O001O00000000000000000000000000O100O1O1O1CWNVEk1k:VNQEl1o:8000000000000GkM[EV2e:kMZEU2f:lMYET2f:oMXEQ2h:PNWEP2h:RNWEn1h:;O1O1N2N2@`0N2O1NdMYFX1f9fN]FZ1a9dNcF\\1Z9]NPGc1o8XNWGh1h8WNZGi1h8SNZGm1h8oMZGQ2h8kMZGU2n90DoM^EQ2`:QN`Eo1^:SNbEm1R8jMiG?g1M]Nj1T8_NWIJeNg1U8aNPILjNc1V8eNiHKQO`1W8gNbHMVO\\1Y8kNYHM]OX1[8POQHIDW1\\8=dGC]8=bGC_8d2001O[O\\KdHc4]7aK_H^4c7cK[H\\4e7dK[H\\4f7dKXH]4j7bKSH`4n7_KQHb4P8^KnGc4S8:1O00O1001O000fKPHY3P8aLYH\\3d7_LgH^3T7_LWI^3i6VLeIh3R8M3M2N2N3M2N3M2N2N3M1O2N2N2N2N:F001O0000001O00UMRNYJn1g5ZNRJe1n5cNjI]1V6hNeIX1[6jNcIV1]6mN`IS1`6oN^IQ1b6RO[In0e6TOYIl0g6WOVIi0j6ZOSIf0m6^OoHb0Q7BlH=T7FiH:W7JeH6[7MbH3^71^HOb76YHJg7<QHFj7fMRHW5k7600McJXH]5h7cJXH]5h7cJWH^5i720000O100001O001`JVH]5m7O001O0000000000000000KeJZH[5f75000000000000000000000eJcHh4]7UKgHj4Y7UKiHj4l700000001O4L1O1O001O0000O100O1O1M3L4L4K5M36J1O1O00H800001O000000O1N2O1O1O10000O1O1O100000_J\\HS1NQ3k7oLWHP3i7oLYHP3e7QM]Hn2d7PM]HP3b7QLUHk0;S3e7kL\\HU3e7iL\\HW3d7hL\\HY3d7fL\\H[3d7dL\\H]3d7aL]H`3c7]L_Hd3a7ZL_Hh3a7VL`Hk3a7RL`Ho3`7nKbHS4^7kKcH4@b3l7VLhH3J_3U9N1O2N", "size": [427, 640]}, "area": 75100, "iscrowd": 0, "image_id": 142238, "bbox": [0, 241, 640, 186], "category_id": 193, "id": 17}, {"segmentation": {"counts": "S`V2<j:4L4M3[O[OaFi0\\9XObFl0\\9UOcFl0[9UOdFl0[9VOcFl0[9UOeFl0Y9YObFi0\\9c0N3M2N2M3O2N1O1O2N1O1O3M201N2O1O1N2O1;DL5K5N6K4K6J6J2000]MWHb1k7ZNXHd1k7YNWHe1l7WNWHg1l7UNWHi1l7SNXHj1j7RNZHl1c8N3M3L4L5J5TOl0CQjW4", "size": [360, 640]}, "area": 3512, "iscrowd": 0, "image_id": 439180, "bbox": [200, 160, 53, 140], "category_id": 1, "id": 18}, {"segmentation": {"counts": "bof51>1X:8]EKb:>O001O100O1E;0O1000O10O2O1O0O2O2M3N3M2N4L1O1O1O1O2N2O3JP10lN8H8O10010N201NN2M4L3M4LUkj0", "size": [360, 640]}, "area": 797, "iscrowd": 0, "image_id": 439180, "bbox": [520, 160, 43, 77], "category_id": 1, "id": 19}, {"segmentation": {"counts": "]69o:^1bNO5K4L16K1O2NN2N2CcFlNb97[F8j:EUVl6", "size": [360, 640]}, "area": 538, "iscrowd": 0, "image_id": 439180, "bbox": [0, 205, 13, 63], "category_id": 1, "id": 20}, {"segmentation": {"counts": "i[g3>h:2M4L3YOZOhFk0CVO\\90nFm0DUO^9NmFU1R9lNmFU1S9kNkFW1T9jNgF[1Y9:00L4N2000O01000O100000O0100000001O2N10OXNeF13Y1X9fNnFZ1R9fNoFY1Q9gNPGY1o8gNRGX1m8iNSGW1n8hNSGW1n8gNUGX1_9N2N100O2O0O3N3WOfE<d:00O2O0O5K6IaZg2", "size": [360, 640]}, "area": 2282, "iscrowd": 0, "image_id": 439180, "bbox": [339, 151, 52, 70], "category_id": 1, "id": 21}, {"segmentation": {"counts": "Pki15P;3N3M2M3M3M3N2M3M3N2N2O1O01N1O2NSFTOa9R1WFQOi9W1001O1O1O001O1N2O1O1ROPFb0\\:O1O1N2O1N4L7IP`j4", "size": [360, 640]}, "area": 1005, "iscrowd": 0, "image_id": 439180, "bbox": [164, 160, 36, 44], "category_id": 1, "id": 22}, {"segmentation": {"counts": "fTo2:`0Kh9`0jEES:i00OO1OCPFDQ:<QFBn9>UF@l9?VF^Oj94PF39Gf91YF5f:N2M[P10foN1N2[OMTF4k92nE0R:5hELW:c0O1O1O1O1O10O12N2N2M3N3M2N1O001O001O0010:E1O1O101O[NiFX1W9gNjFY1V9fNlFY1T9fNmFZ1S9eNoF[1P9aNTG_1\\9O1O0030001O00001M3M3M1N101N2O0CnEBS:5WFHk9O_FOkUY3", "size": [360, 640]}, "area": 2493, "iscrowd": 0, "image_id": 439180, "bbox": [270, 153, 71, 113], "category_id": 1, "id": 23}, {"segmentation": {"counts": "nQ[65n:5K6K4N2M3XO[OkFe0S9@jF?V9EgF;X9IeF7Z9McF2^91^FO[9@fFX1\\9hNdFU1^9mNaFQ1a9PO^Fm0e9SO[Fj0g9:2FWFROl9n0TFQOl9P1UFmNm9S1310O011O2N1O1O100WOiE?X:@iE`0X:^OiE`0Y:^OhEb0Y:]OhEa0Z:^OgE`0b:O1NVd8", "size": [360, 640]}, "area": 1250, "iscrowd": 0, "image_id": 439180, "bbox": [577, 141, 38, 79], "category_id": 1, "id": 24}, {"segmentation": {"counts": "kbX42V29^6JWI?g6FmHc0R7@bHj0\\7XO_Hm0`7SO^HP1`7RO^HP1a7PO]HS1a7nN^HU1_7mN_HU1`7kN^HM@f0Q8^O^HL8O[76[HJ>NV79XHLe0HT7=RHMn0Do6`0PHNU1^Ol6^1WI`Nh6_1`100001O2N2O1O01000O100O010001O001N101O1O0O2O000O1dN\\FS1e9mN^Fo0d9oN_Fm0c9SO_Fj0b9UOaFh0`9XObFe0_9ZOdFc0S:L4M2N3Jd`2M__M7I7J6L4L4L4L43M3M3J5K2N1N2O1N3N1N2O1O1N3N1N2Omij1", "size": [360, 640]}, "area": 2955, "iscrowd": 0, "image_id": 439180, "bbox": [388, 147, 84, 124], "category_id": 1, "id": 25}, {"segmentation": {"counts": "dji25o:5O1FGbE;\\:GbE;]:GaE:]::O2M2O1O0010O01OFiECX:MjE60KW:LlE8OMS:IoE91N[:MfE5f:2O1N00O1Ogfn3", "size": [360, 640]}, "area": 496, "iscrowd": 0, "image_id": 439180, "bbox": [255, 172, 24, 48], "category_id": 1, "id": 26}, {"segmentation": {"counts": "o\\U5>g:4N1O1O001C]OTFd0k9^OTFb0l9^OSFc0l9@RF`0n9BPF=P:?N1O2O001O1O1001OO010O0101hNSFQ1S:0O11O0011O0O0102M4M001N3O05K1OO01gETOQ:Q12O0O1QO_F5^:K4LReZ1", "size": [360, 640]}, "area": 1521, "iscrowd": 0, "image_id": 439180, "bbox": [470, 150, 48, 92], "category_id": 1, "id": 27}, {"segmentation": {"counts": "Ukn02]:6TFKi9<QFFk9?SFBj9a0TFAj9;UF^OO8i95fFLW9NRG0m8K\\G2o9O1Nj]39laL2M2O2C@nEb0R:_OlEb0S:_OkEd0S:^OkEe0R::N3M3L4K4N101O0O2O1O001O0101N10010`N^FV1c9iN_FV1`9iNbFV1_9iNbFW1^9gNcF[1\\9dNeF\\1Z9dNfF]1c9POXF?h9A[F<d9D_F;`9DiF6U9IQG5k8KVG8g8HYG=b8B_G?_8AbGa0\\8^OeGQ1l7nNVHQ1i7POWHP1i7oNXHQ1h7nNYHR1g7mN_Hl0c7SOgHb0[7\\OPI8[9ETVY5", "size": [360, 640]}, "area": 2202, "iscrowd": 0, "image_id": 439180, "bbox": [87, 163, 71, 116], "category_id": 1, "id": 28}, {"segmentation": {"counts": "lRb21S;6L3N2O1O100O0TFHi88VGKg87VGKj88RGIm8<mFGR9=iFEV9?eFDY9Y1M2O2N010OQNhFl1[91N10N1O4L3eNbFf0a9XOdFb0`9ZOdFa0`9YOeFf0o905K5K6J1M3Nm`R4", "size": [360, 640]}, "area": 1222, "iscrowd": 0, "image_id": 439180, "bbox": [233, 173, 35, 90], "category_id": 1, "id": 29}, {"segmentation": {"counts": "Sk58j:7L4N2M4SFZOS9j0fF[OX9h0aF^O[9Z1L3O2O0O2ODhFgNY9W1mFdNU95iFe06TOR94nF5LJ7LP92VHOb9O01n]d6", "size": [360, 640]}, "area": 672, "iscrowd": 0, "image_id": 439180, "bbox": [16, 205, 19, 63], "category_id": 1, "id": 30}, {"segmentation": {"counts": "_io2125l:4O1O101O1O00001O01O1O2N5Ild<MY[C2N1O2N3M4L4M3M3N3N2N2L3M2N101O1<A1O001O4\\O\\E<h:O1O3Lne7KUZH4O2N2O1O001O2N2N001O0001O00001O1O2M3M3LM222N3M2O1O1ON2N2O1N3N2M3NUV:3iiE2M3N2N2N2N1O2M3M5K10O100O1000000O20J5O2N1O2O001O001O2N2O1O01N3M1ImEWOU:g0mEWOU:h0<I5KkQ8LXnG2N4L2O1O1O000000000aEEQ:;mEKo95oE0n9ORF5k9JUF;h9BYFb0d9_O[Fd0b9d0M3M1OIlF\\NS9c19O10000O100@[F\\Of9c0cFROa9h0c00001M2O2MOG:1O1O10O0101O1O001O1O2N01N2N3Ld<JcC10001N3M2O2N1O1AKiE7T:`0N000JO7N2O1GiEAY:?iE]OY:b0iE\\OX:d060ABTF>k9`0O1OOPFlNP:R1RFnNn9o070XFQOW9o0a00001O1N3M4KXl8^O[TG8H2N1ZME\\J>d5BZJ`0f5AVJb0f5\\OQH4a0KS1f0[6CaHGP1j0_6@_HHl0m0e6@YHEo0l0i6NUI2l6NSI1o6OPI0S7OlH0W7OlGZO=X1Z7]OTHA?U1^7G`H?`7\\NSHl08d1X7VNcHR2X7PNfHS2W7U1ZOb0N2N?A2O1O1O000000POTJdLm5[3UJcLl5\\3XJ`Li5^3YJ`LP1", "size": [360, 640]}, "area": 7839, "iscrowd": 1, "image_id": 439180, "bbox": [272, 142, 368, 178], "category_id": 1, "id": 31}, {"segmentation": {"counts": "YlQ2a0g:O10000000000000001O000000000O100000000000000000000000000O10000000000000000003M2N3M3M>BN3M2O1M3N2O100O11O1O001O1O001O1O1O1O2N2N3M2RFgNi9^1NoNYFa0g9XO_Fc0g9WO_Fe0T:00G`EIa:6aEH`:8bEE^:;800O1000002O1N2N2O1N2OZkP4", "size": [360, 640]}, "area": 1680, "iscrowd": 0, "image_id": 439180, "bbox": [187, 145, 86, 49], "category_id": 8, "id": 32}, {"segmentation": {"counts": "mk<2f:1eE2V:4fENV:7gEKU:g0K4L4L5K4O101O0O101O0O102N2M2O2N1O000000000BSNaGl1`8[NYGe1g8>0000001N10000000000O10000000000O1000000000000O1000000O1N2M3N2N2M3N2N2M3N2O1N2O1N2M3N2N2K5O1N2N2EcEI_:7bEEa:6;O1O1O1O1O100O10000O1000000010O1O1O1O2N2N001VEFd:;ZEHd:9[EJb:6^EKa:>01O1mE^O^9b0bFFV9;iFEW9<hFDX9<iFCW9>hFBX9?gFAY9?gFAY9`0fF@Z9`0gF_OY9b0fF^OZ9c0eF]O[9c0eF]O[9d0dF\\O\\9e0bF\\O^9W10001O0000\\O_F@b9a0bFUOc9h0`0M3N2N2M3M3M3N2M3M3N2N2O1O10WmQ5", "size": [360, 640]}, "area": 5791, "iscrowd": 0, "image_id": 439180, "bbox": [36, 159, 143, 77], "category_id": 8, "id": 33}, {"segmentation": {"counts": "Sgm12V;2N101N4L:F9nEWOS9`100O010O001O001O102Ml0TO4L5K2O1N2M3L4000000000001N5J9^H\\Lo6n3100eNmH_NT7\\1TI`Nn6[1YIbNg6Z1UJmMl5T2d1101jGdM[7f2RHhMi7R3K1N2N20O0M4fNTIPNQ7h1ZIQNj6i1_1I7H8I6J7JlU_4", "size": [360, 640]}, "area": 4363, "iscrowd": 0, "image_id": 439180, "bbox": [175, 203, 57, 152], "category_id": 19, "id": 34}, {"segmentation": {"counts": "YZS63T;1O1H8M4M2F^OlEe0S:]OiEg03XO5OX94^FZ1b960000000O1_Oa0K5]OhE5Y:IlE2V:NmEJW:6>L4NToe0", "size": [360, 640]}, "area": 573, "iscrowd": 0, "image_id": 439180, "bbox": [555, 182, 22, 54], "category_id": 19, "id": 35}, {"segmentation": {"counts": "^Pm23V;2M3N1N200O100000N5I\\SP4", "size": [360, 640]}, "area": 96, "iscrowd": 0, "image_id": 439180, "bbox": [264, 206, 11, 21], "category_id": 19, "id": 36}, {"segmentation": {"counts": "ZRg1:7NR:l0I5L:aFgN[8]2E9nNRMZIW3`6mLWIW2OWNk6GiHS2d0UNa6U2hIeMX6X2lIfMT6X2QJeMP6X2SJgMm5X2UJfMm5W2VJgMk5X2b10lHjMW51RIo1\\1\\Na5DVIm3i6RLYIm3g6RL[Im3d6TL^Ik3_6WLdIf3Z6\\LjI`3U6aLQJ<AT1Z9E;E:J6K4L4K4M4GTE1]dn4", "size": [360, 640]}, "area": 2505, "iscrowd": 0, "image_id": 439180, "bbox": [156, 192, 33, 146], "category_id": 19, "id": 37}, {"segmentation": {"counts": "PUP33U;1O10001N1O1WEOZ:a0N1mE\\O`9W1O001eFoN]8Q1\\GXOb8h0\\G[OK[Ob8Z1^GH`8d1cIYMQ4S3`KPM`4T3XKPMh4V3nJnLR5a3ZJdLf5f3kI_LU6Y4100XOkI\\LV6_3UJ[Lj5Q3RJhL>Ne5a3WJ]LY6k2WImMMKe6T2cIeNc6U1_IiNd6T1SJhM\\6W2VIfMEOH8X7m1YIjNl6Q1RIPOR7m0gHYOZ7g0_HiN6C]7Y2SI]Mo6_2aH`M90V7Y2fHnMi7T2oGRNP8c21O1O2lNmGoNT8i0\\HaN]O3Z8X1^HaNP8\\1R1L4K6J8H7Ji_^3", "size": [360, 640]}, "area": 4160, "iscrowd": 0, "image_id": 439180, "bbox": [273, 184, 52, 164], "category_id": 19, "id": 38}, {"segmentation": {"counts": "\\ad58P;2M2XEF`:d0M4K4M4M3L5K3L4M4L:F9G:F1O10O0O1mNT1NVGgNg7X1SHPOl7o0gG_OZ8g10O010^O_G\\Nc8^1f0M3N2O2G8L4M3M4M4L3GaEFb:2fEJ]:Ol\\n0", "size": [360, 640]}, "area": 1904, "iscrowd": 0, "image_id": 439180, "bbox": [513, 194, 40, 84], "category_id": 19, "id": 39}, {"segmentation": {"counts": "]dR56Z:3nE5P:b0GROVFQ1i9QOTFP1m96O0001O1O0000O6K3M2N2N3M6J8I5I4N3L>CO100O1O1N1N3M2105J01O1O100YOeG_N^8[1jG`NX8Z1TH^Nm7]1S1J5K6H:B<L`a^1", "size": [360, 640]}, "area": 2742, "iscrowd": 0, "image_id": 439180, "bbox": [462, 187, 45, 103], "category_id": 19, "id": 40}, {"segmentation": {"counts": "dT\\43S;g0]E[OV9i0hFYOU9j0hFYOT9k0jFWO?Ek7X1bGVO>H_OJZ8[1gGTO<MCET8Q2TH`NGAP8P3PHRMj7Y3M4M2N2N1N2O000001O0UOeHiM[7S2mHiMT7S2RIjMn6S2YIiMh6R2cIdM`6Y2Y1K6N100000000000N2M2N3N2N2THTN[6P2^IaNS6f1_IdN^6S3O2O0OC`IVL^6h3hIULW6i3PJTLP6h3VJULj5b3S1I7N2ZNVHGP8FRHYO5j0n7KPHUO9i0k70PHRO;i0h73hHHZ76kHFW78mHCU7;PI^OU7>l1N3M4L_FIW83mGMS8OQHO_dn1", "size": [360, 640]}, "area": 5333, "iscrowd": 0, "image_id": 439180, "bbox": [398, 181, 64, 157], "category_id": 19, "id": 41}, {"segmentation": {"counts": "\\]g3<a:GaEg0W:;I4L4L7I6J5K4M5Ja0_Oe0[O3M1O100O0K6O10QOjHlMV7R2RIgMo6W2Q1O2O11kG_Ma7b2ZHeMc7[2YHlMd7k2101O0<D00O2O0000001[L[Ij1C_NU8Y1QHbNU8i0b1@`0Fhij2", "size": [360, 640]}, "area": 3612, "iscrowd": 0, "image_id": 439180, "bbox": [339, 213, 42, 124], "category_id": 19, "id": 42}, {"segmentation": {"counts": "obP16k:>B9H9H7L4K6I6J6K5M3L4M3L4M4K4M4O1O0O2O2M2N3L3N3Ma0^O0100O10O01O0O2N1O2O0O1WOj0K4N3M2N3K4L5J7E:L4M3M3M4L5K6H8HP^]5", "size": [360, 640]}, "area": 4508, "iscrowd": 0, "image_id": 439180, "bbox": [92, 204, 54, 144], "category_id": 19, "id": 43}, {"segmentation": {"counts": "b][6a0i0@P9g0jF]OS9g0iF\\OV9g0eF\\OZ9g0`F]O]9Y1LN3B>B=2N3N2M3N2M4jFiNV8Z1gGhNX8[1eGgNQ8JbGn1NZNa8H`G[2a8fM\\G[2e831O010O2N1O1hNhG_OY8=WHVOk7f0]1L_R;", "size": [360, 640]}, "area": 1511, "iscrowd": 0, "image_id": 439180, "bbox": [578, 179, 30, 95], "category_id": 19, "id": 44}, {"segmentation": {"counts": "old66n:4L4M3\\Od00000001N2N101N2N2N3L7Hg_6", "size": [360, 640]}, "area": 421, "iscrowd": 1, "image_id": 439180, "bbox": [605, 184, 16, 37], "category_id": 19, "id": 45}, {"segmentation": {"counts": "ggd01R;5LKTE6i:6001ON20000NCYE=g:21O1ON22N001OO11O0000000000NDXE<h:DXE<h:20000000000NBZE>f:20000O1000000000000O1E^OPFb0P:_OhEO1e0U::00O1001OO10000O1001O001Ob0^O1O001O00000000O1O100O1O1VOj01OO100O11O0000O10000002N001ON200NgNUFY1k9gNUFY1k920000001O00N200001OO1002N7I1O2N1ODQO`Fn0^9VO`Fj0`9XO^Fh0b9YO\\Fh0d9YOZFh0e9ZOYFg0g9_O]F7d9]OhFb0o90001O00001OJ6UOk0I7I7M3O1O12NN200001O4L4L5K2N2N2N2N2N2N2N2N2N2N3M6J9XObE4j:O00001O00nNMoF3o8T1O10ROVF>l9XObFb0Y:I3M3M3M2N00O1XO=iEEX:e00000O10000O100O1O100AQOdFP1Q9\\OmFe0S9\\OdFl0\\9`00000000000000000N20000RObNPH`1P8aNlGb1T8_NmG_1T8`NkGa1U8`NdGf1\\8c000001O000000001OOO4L101OGbMeGb2\\833N01O1O1N2O001N2O1001N3M6K2M2`M]GX2l8N4L<B6H:Fc0\\O^]1@UXN2S:2TF5ENZ:LhE29:l9A^F7c8I]H6c7J_H0V8<lFEV92VF3?KZ92UGMl81Th03lXO1K63Ie\\19hXNDm9h0kEZOS:m0O2O1N2O12jNPFP1T:O2OO0101OO0000O01KTOPFi0S:61M210NJUOoEk0T:50N4M3L7K4K4K402Jmk3MUTL1O02Og_48R`K001OO2O001O\\OJVF6h9MXF2f91YFOf94YFKf97YFIh99VFFj9`0oEAS:b0gE^O[:f0001N1N2O2N2M4M002K4L]Tc2", "size": [360, 640]}, "area": 11074, "iscrowd": 0, "image_id": 439180, "bbox": [58, 192, 345, 168], "category_id": 125, "id": 46}, {"segmentation": {"counts": "0]69\\J`3d5R1002N5K001O1O1O1O1O1Oh0XO1OO1O1BaLRI`3h6gLUI[3h6d0O1N2O1O1M3M3O100O100001`KdIR4]6kKiIQ4W6mKoIo3S6nKoIQ4d6000IoKWIQ4Y6oKnI2HP4V6TLnINLn3R6YLoILNk3o5kLQJU3k5oLTJR3h5Y1L4L4O10000OmKeJ\\NMm3^5gMgJY2Y5gMiJ\\NJh3\\5nMlJR2T5oMlJP2T5RNiJo1V5SNiJm1W5UNhJj1X5XNfJh1Z5XNfJh1Z5XNfJh1Z5XNfJh1Z5WNgJi1Y5XNgJg1k4[L]Kn1If1j4cLVKg10f1j4hNWKW1i4iNWKW1i4jNTKX1l4hNRKZ1o4eNQK[1o4_2000000000000000000000000000000000000000000000000000000000000000000000000000000000000000000000000000004L00O1OVKgI00O0a4X6`KPJ`4\\603MN2010O1ON2O1O1N2O1N2IXKjIl4V6300000000000000000000000000000000000000000000000000000000000000000000000000000000000O100001O1O1O^O\\J`Kd5`4\\JaKc5_4]JbKb5^4^JcKa5]4_JdK`5\\4`JeK_5[4aJdK`5\\4`JbKb5^4^JaKc5_4\\J`Kf5a4`00000000000000000000000000hI_Ki5a4WJ_Ki5a4WJ_Ki5a4WJ_Ki5a4WJ_Ki5a4?00000000000000000gIaKi5_4WJbKh5^4[JaKc5_4_J`K`5`4d00000001O000000000000000000000000000000000000000000000fIaKk5_4oIgKQ6h40000000O100000000002N2N2N2N2N2N1OO1O10000000000001O1O2N4^J]JW5h52O1N2[O`JaKa5^4eJ[K]5e4hJUKY5j4c0O1O1O1O1O100000000O10000000000000000001O0000001O1nIUKe5l4ZJVKd5k4[JWKc55WJX45dKc54XJY44eKb51[J[41eKd50[J\\4MgKh5GcJm4]5RKcJo4]5QKcJo4k50N22O1ON3M4LYKSJX4j5gKYJX4f5fK[J\\4f5\\KVJN4g4e5[K`Jh4_5UKcJm4j52NO4K2N2ZOdI^Lf6[3\\IaLe6CZIk31aLf6EXIi33aLg6a3YI]Lg6d3ZIWLk6i3;O1K3O113M0O2ON2003^L[H[3P8I0O4M3M1RMhGj2[800030L2N12RMgGi22ZMW8a2iG^MW8c2iG\\MY8c2fG^MX8c2iG]MW8d2hG\\MY8d2fG\\MZ8i21OSHWM\\7h2eHXMY7i2gHXMX7h2hHZMU7h2jHYMV7f2jH[MS7g2mH]Mn6e2QI_Mj6c2UI_Mk6a2RI_Mn6d2oHVMJIS7MoHV30UM1Gn62oHl24\\MT7m2nHQMT7m2oHoLS7P3oHnLP7T3QIiLR7V3`002N1OlHlLT6T3kInLT6S3kIkLW6V3gIkLY6V3eIjL^6S3cInL]6NjHP3V8N2N3M4L3M4L3N1O6K000O2OO0O20001L3O22M2OL4O0010OO100\\GcM[8_2eGcM[8\\2cGeMW8OiG[20eM\\70QI9BR20fMV77VI3Do10gMU78VI4El1OiMV77VI5Cm10gMW77XIh2h6XMXIh2i6YMVIe2k6\\MmHCJ13n2W7_MgHJ1f2Y7`MeHL0e2[7_MgHk2Y7SMhHn2X7SMeHo2[7?]OZLXIM9h3a6YLWI06g3c6ZLVIO7h3^6UL]I9OH2e3f6iLWIB3d3f6kLWIZ3j6a0013MO10fKVIV4n602NN30001O2M1JeK]I]4V6cKkI3LN1_4T6oKmIV4l5h0K1OM3O1O1O1O1CRJ_Ko5`4SJ_Km5a4SJ^Kn5a4UJ]Kk5c4WJ[Ki5d4>O1O1000000001O2N001O00G9OjIaKe5^4ZJeKe5Z4]JeKc5[4e0000000000000000000001O00000000001O00000000000002OO100M4N12^K^IZ4g6N01003M2OO0012iKPIR4W7L00L40mLoHo1S7mMoHS2?SM1NS55_JLK;3d2=VM0KS55bJKK:5f29YMOIT51jJLE48P32ZM1Gj5LTJP42SLi5MUJR41mKm51RJT4g62L3NULYIY3d6hL^IZ3`6dLaI[3^6_L[IL6g3]6_LiIa3Z6[LhIV3MeL[63jIW3Z701O0J601O1O2O1O0SMjGh2\\8UMfGf2^8AfGPNY8P2`0O1OTHkMg6U2WImMi6S2TIQNl6n1TIRN[OKU7R2`ISNZOLV7Q2`IRNZOMV7R2`IQNVOKL3\\7T2aInMUO3Z7P2_IoMTO3Z7S2_IVN_6P2\\IRNd6Z33K02OXOiH]MU7@iHo29XMT7IbHm2?WMQ7h2SITMn6k2h0O0HmG_MS8a2nG^MR8a2oG_MS8_2nG`MR8`29`M^G]2c84I`MdGb2Z8]MeG10a2X8fMhGZ2Y8fMfGY2\\89L302O2O0K5O11ON2WHhL]7]39NM3OO015KM300O10001O1O15LO4XH`Lb77\\HV3^7fLgHV3]7iLcHV3]7kLbHe2o7ZMQHf2P8ZMoGf2S8XMnGg2R8[MlGf2T8YMnGf2Y81001O1O01M300RN", "size": [360, 640]}, "area": 91045, "iscrowd": 0, "image_id": 439180, "bbox": [0, 0, 640, 243], "category_id": 184, "id": 47}, {"segmentation": {"counts": "XaZ14T;00O1OnDO00O0i:0XE8h:403MN2001O1ON2O1O1N2O1N4Jddo12^[PN0O100J8M010N20N22N2NO1O1OgEEg9;XFHf98XFIi99oECN4S:9oELR:5kEMU:b01O12NO1O16JNmEPOR:P1oEoNQ:R12N2001O1OO1O13M001ON2003nEkNk9`1I003M3M1aFYN[9j10003MO1O12eFTNV9T2KO11ON2001O001O1OO100O11ON2O1O12NO1KlFVNT9i1PGUNo8h1:1O00N21O002N1O000000002N1hFQNU9Q20001O2N1O2N1O005K00001OO1N20000M3O13M2NM300001OO100N22NJUGPNj8T1VGYO9Ba8n0^G^O3D^8m0`G^O4E[8m0aG^O5C[8o0`G@P9`0PG@P9a0QG^On8b0SGVOCJ13X9m0UGQOJ1Q9n0UGPOL0P9P1TGROV9n0hFSOY9m0hFPOZ9P1?]OoECM9S:6nEB06R:8oEAO7R:4kEG9OH2T:7ZFFB3T:6[FGk99b0O13MO10TEHh:<02NN21O1O1O00K[EGe:N[E33LN1U;1fcb0OY\\]O001ON2003lD0j:70N2O12N1OO1O12SEFh:a0L00L40WFEe8=WGEi8:`FHLK;3Y98aFJKK:5Z96_F0LE48b9i0[FXOf9g0ZFYOg9f0YFZOh9S10N2OdFjNh8U1YGmNe8U1YGlNf8S1TGfNL6R9R1TGTOl8o0PGSOo8m0oFUOQ9`1100O1O100001O1O0mFPNn8V2oFlMl8X20O1000000001O1O00O1N200M3M3004LO100LPGPNP9P2PGoMQ9R22N2O1N200002N00NiFUNU9k14IhF\\NZ9b1eF]N10Z9_1mFaNS9`1mF_NS9b19L4O1001OL4002NO1M33MN200O15KM300O1000000006J1O4aF]NQ9c1kFbNT9_1kFaNU9^1lFaNU9_1jFaNW9_1iF`NX9a1fF`NZ9_1hF_NY9a1fFaNY9f11001O1O00N21O", "size": [360, 640]}, "area": 12912, "iscrowd": 0, "image_id": 439180, "bbox": [121, 0, 519, 79], "category_id": 187, "id": 48}, {"segmentation": {"counts": "S8U3T8O00O14L002N3M00O1EUMXHl2f7<N2L400IfLaHY3^79N2O11O2jLcH]2`7\\MeHc2]7VMiHi2l7O1O001O001OCYMWHi2g7\\MUHe2i7^MVHb2U7SNlHl1Q7XNnHh1R7XNoHg1Q7ZNmHg1S7W1O1000000O1000000001O005lKiHm3Y702SLfHh3]701OO1001O00000O1K5L[HdLb7OaHY3e7gL\\HX3d7hL\\HY3c7gL^HV3d7jL\\HV3c7lLZHV3f7jLXHV30hLh72XHV3j75O1ON13N001OO11O0O10000000N[HaLe7_3[HaLe7_311000dM[HU1e7RNaH5Kh1d7QNhH1Fm1b7oMmH2Bl1KlMe75QI1Am1_7RNSIO@m1Z7UNhIj1V6WNlIg1R6[NoIe1o5[NSJe1l5ZNVJf1k5VNYJi1e7N2N2M3C^FPOd9n0]FjNO1i9Q1<N3L3N3N2L3N3M4K4M4M2M_X51^gJ1O2M2L6L3E;N110000002N001ON200NhETOX:l0hETOX:l0FTO\\Fl0d9TO[Fm0e9;10N1OO11N2O25QOZFOi:GRQ1>^nN7I6J002O1O1N101O2c]P1jN`coN2O1O1O1N2O100000000O100000000O1O100O1O1000BYE;j:0000000WOFdF:U:000O1VODPF4b08c9D]F=\\9ITFK=;Z:1O1K5O1YO]OiFc0n90000000[OHZF8g9LTF4R:>1O001O00O100O1G90000000000O100O10000O1O1N2O1M300N21OO1N21OO100O11O00O13MO1<Dd0\\O3M0000O1000000QO^OWGc0h8DRG<m8KjF8U9n0N2ObNiFm0W9oNPGn0P9nNWGo0a9000O1<D00000000O100WODfF<V9IiF7n84jF2e8a1G9M3N2N24LO100004L0000001O1O000000O1002N1O1`M^GX2c8cM^G1OO0?0[1e8XN_G72HJd1e8\\N`G47KFb1`9^NaF_1a9aNaF[1h9N3M2N2N1O1O1O000000VOQOZGP1b8XOZGh0c8_OYGa0c8FZG:c8NWG3f8Y1L4M300000000O100000000000YNnG8T8B]H1h7AbH>T90O100O1@^OZFb0b9D[F=a9I]F7]93_FMV9X1L4O1G9L4M3O1N2N2M3O1001O00O1[ORMPIn2P7UMlHl2T7UMkHk2f6WMSI05i2h6gMVIZ2k6fMTIZ2l6gMRIZ2o6fMPIZ2P7hMnHX2R7iMlHX2T7iMkHW2U7n0004L3M2N2N3M6J8H6J3M4L?A00001O0000N2L41O6J1O00000000YORNTHn1h7\\NRHd1k7n0L4K5L4D<M3N2L44L2N3QLjHf3]7O0000B\\LXId3h6aLSI_3l6eLPI\\3Q7=004L5K3M3M4L:F9G:F1O1O1OO1A?[OnMbHd1]7VNkHi1T7jMZIV2l700000O1[OlMUHU2h7g0N2N2K5K5L4M3M3O1N2N2O12N2N3M3M4L1OO1O1O1FULVIOJk3\\7O00000000O1O1H800001O00000000?eL^HR2e7hM_HW2c7eM`HZ2c7aM`H^2c7\\MaHc2S8O1OC=_Oa0G900001O000nLgHU2Y7hMiHY2X7dMjH\\2b7UM`Hl2m71O1O1O100O1O1O1O1^OmLnHT3o6PMPIP3Q7nLQIQ3Q7lLPIT3b700000000000O1O1N2N2N2>B1O5Kh0XO3M1O5K1O1O>B1O1O1O000000000000O1", "size": [360, 640]}, "area": 40197, "iscrowd": 0, "image_id": 439180, "bbox": [0, 219, 640, 141], "category_id": 193, "id": 49}], "categories": [{"supercategory": "person", "color": [220, 20, 60], "id": 1, "name": "person"}, {"supercategory": "vehicle", "color": [119, 11, 32], "id": 2, "name": "bicycle"}, {"supercategory": "vehicle", "color": [0, 0, 142], "id": 3, "name": "car"}, {"supercategory": "vehicle", "color": [0, 0, 230], "id": 4, "name": "motorcycle"}, {"supercategory": "vehicle", "color": [106, 0, 228], "id": 5, "name": "airplane"}, {"supercategory": "vehicle", "color": [0, 60, 100], "id": 6, "name": "bus"}, {"supercategory": "vehicle", "color": [0, 80, 100], "id": 7, "name": "train"}, {"supercategory": "vehicle", "color": [0, 0, 70], "id": 8, "name": "truck"}, {"supercategory": "vehicle", "color": [0, 0, 192], "id": 9, "name": "boat"}, {"supercategory": "outdoor", "color": [250, 170, 30], "id": 10, "name": "traffic light"}, {"supercategory": "outdoor", "color": [100, 170, 30], "id": 11, "name": "fire hydrant"}, {"supercategory": "outdoor", "color": [220, 220, 0], "id": 13, "name": "stop sign"}, {"supercategory": "outdoor", "color": [175, 116, 175], "id": 14, "name": "parking meter"}, {"supercategory": "outdoor", "color": [250, 0, 30], "id": 15, "name": "bench"}, {"supercategory": "animal", "color": [165, 42, 42], "id": 16, "name": "bird"}, {"supercategory": "animal", "color": [255, 77, 255], "id": 17, "name": "cat"}, {"supercategory": "animal", "color": [0, 226, 252], "id": 18, "name": "dog"}, {"supercategory": "animal", "color": [182, 182, 255], "id": 19, "name": "horse"}, {"supercategory": "animal", "color": [0, 82, 0], "id": 20, "name": "sheep"}, {"supercategory": "animal", "color": [120, 166, 157], "id": 21, "name": "cow"}, {"supercategory": "animal", "color": [110, 76, 0], "id": 22, "name": "elephant"}, {"supercategory": "animal", "color": [174, 57, 255], "id": 23, "name": "bear"}, {"supercategory": "animal", "color": [199, 100, 0], "id": 24, "name": "zebra"}, {"supercategory": "animal", "color": [72, 0, 118], "id": 25, "name": "giraffe"}, {"supercategory": "accessory", "color": [255, 179, 240], "id": 27, "name": "backpack"}, {"supercategory": "accessory", "color": [0, 125, 92], "id": 28, "name": "umbrella"}, {"supercategory": "accessory", "color": [209, 0, 151], "id": 31, "name": "handbag"}, {"supercategory": "accessory", "color": [188, 208, 182], "id": 32, "name": "tie"}, {"supercategory": "accessory", "color": [0, 220, 176], "id": 33, "name": "suitcase"}, {"supercategory": "sports", "color": [255, 99, 164], "id": 34, "name": "frisbee"}, {"supercategory": "sports", "color": [92, 0, 73], "id": 35, "name": "skis"}, {"supercategory": "sports", "color": [133, 129, 255], "id": 36, "name": "snowboard"}, {"supercategory": "sports", "color": [78, 180, 255], "id": 37, "name": "sports ball"}, {"supercategory": "sports", "color": [0, 228, 0], "id": 38, "name": "kite"}, {"supercategory": "sports", "color": [174, 255, 243], "id": 39, "name": "baseball bat"}, {"supercategory": "sports", "color": [45, 89, 255], "id": 40, "name": "baseball glove"}, {"supercategory": "sports", "color": [134, 134, 103], "id": 41, "name": "skateboard"}, {"supercategory": "sports", "color": [145, 148, 174], "id": 42, "name": "surfboard"}, {"supercategory": "sports", "color": [255, 208, 186], "id": 43, "name": "tennis racket"}, {"supercategory": "kitchen", "color": [197, 226, 255], "id": 44, "name": "bottle"}, {"supercategory": "kitchen", "color": [171, 134, 1], "id": 46, "name": "wine glass"}, {"supercategory": "kitchen", "color": [109, 63, 54], "id": 47, "name": "cup"}, {"supercategory": "kitchen", "color": [207, 138, 255], "id": 48, "name": "fork"}, {"supercategory": "kitchen", "color": [151, 0, 95], "id": 49, "name": "knife"}, {"supercategory": "kitchen", "color": [9, 80, 61], "id": 50, "name": "spoon"}, {"supercategory": "kitchen", "color": [84, 105, 51], "id": 51, "name": "bowl"}, {"supercategory": "food", "color": [74, 65, 105], "id": 52, "name": "banana"}, {"supercategory": "food", "color": [166, 196, 102], "id": 53, "name": "apple"}, {"supercategory": "food", "color": [208, 195, 210], "id": 54, "name": "sandwich"}, {"supercategory": "food", "color": [255, 109, 65], "id": 55, "name": "orange"}, {"supercategory": "food", "color": [0, 143, 149], "id": 56, "name": "broccoli"}, {"supercategory": "food", "color": [179, 0, 194], "id": 57, "name": "carrot"}, {"supercategory": "food", "color": [209, 99, 106], "id": 58, "name": "hot dog"}, {"supercategory": "food", "color": [5, 121, 0], "id": 59, "name": "pizza"}, {"supercategory": "food", "color": [227, 255, 205], "id": 60, "name": "donut"}, {"supercategory": "food", "color": [147, 186, 208], "id": 61, "name": "cake"}, {"supercategory": "furniture", "color": [153, 69, 1], "id": 62, "name": "chair"}, {"supercategory": "furniture", "color": [3, 95, 161], "id": 63, "name": "couch"}, {"supercategory": "furniture", "color": [163, 255, 0], "id": 64, "name": "potted plant"}, {"supercategory": "furniture", "color": [119, 0, 170], "id": 65, "name": "bed"}, {"supercategory": "furniture", "color": [0, 182, 199], "id": 67, "name": "dining table"}, {"supercategory": "furniture", "color": [0, 165, 120], "id": 70, "name": "toilet"}, {"supercategory": "electronic", "color": [183, 130, 88], "id": 72, "name": "tv"}, {"supercategory": "electronic", "color": [95, 32, 0], "id": 73, "name": "laptop"}, {"supercategory": "electronic", "color": [130, 114, 135], "id": 74, "name": "mouse"}, {"supercategory": "electronic", "color": [110, 129, 133], "id": 75, "name": "remote"}, {"supercategory": "electronic", "color": [166, 74, 118], "id": 76, "name": "keyboard"}, {"supercategory": "electronic", "color": [219, 142, 185], "id": 77, "name": "cell phone"}, {"supercategory": "appliance", "color": [79, 210, 114], "id": 78, "name": "microwave"}, {"supercategory": "appliance", "color": [178, 90, 62], "id": 79, "name": "oven"}, {"supercategory": "appliance", "color": [65, 70, 15], "id": 80, "name": "toaster"}, {"supercategory": "appliance", "color": [127, 167, 115], "id": 81, "name": "sink"}, {"supercategory": "appliance", "color": [59, 105, 106], "id": 82, "name": "refrigerator"}, {"supercategory": "indoor", "color": [142, 108, 45], "id": 84, "name": "book"}, {"supercategory": "indoor", "color": [196, 172, 0], "id": 85, "name": "clock"}, {"supercategory": "indoor", "color": [95, 54, 80], "id": 86, "name": "vase"}, {"supercategory": "indoor", "color": [128, 76, 255], "id": 87, "name": "scissors"}, {"supercategory": "indoor", "color": [201, 57, 1], "id": 88, "name": "teddy bear"}, {"supercategory": "indoor", "color": [246, 0, 122], "id": 89, "name": "hair drier"}, {"supercategory": "indoor", "color": [191, 162, 208], "id": 90, "name": "toothbrush"}, {"supercategory": "textile", "color": [255, 255, 128], "id": 92, "name": "banner"}, {"supercategory": "textile", "color": [147, 211, 203], "id": 93, "name": "blanket"}, {"supercategory": "building", "color": [150, 100, 100], "id": 95, "name": "bridge"}, {"supercategory": "raw-material", "color": [168, 171, 172], "id": 100, "name": "cardboard"}, {"supercategory": "furniture-stuff", "color": [146, 112, 198], "id": 107, "name": "counter"}, {"supercategory": "textile", "color": [210, 170, 100], "id": 109, "name": "curtain"}, {"supercategory": "furniture-stuff", "color": [92, 136, 89], "id": 112, "name": "door-stuff"}, {"supercategory": "floor", "color": [218, 88, 184], "id": 118, "name": "floor-wood"}, {"supercategory": "plant", "color": [241, 129, 0], "id": 119, "name": "flower"}, {"supercategory": "food-stuff", "color": [217, 17, 255], "id": 122, "name": "fruit"}, {"supercategory": "ground", "color": [124, 74, 181], "id": 125, "name": "gravel"}, {"supercategory": "building", "color": [70, 70, 70], "id": 128, "name": "house"}, {"supercategory": "furniture-stuff", "color": [255, 228, 255], "id": 130, "name": "light"}, {"supercategory": "furniture-stuff", "color": [154, 208, 0], "id": 133, "name": "mirror-stuff"}, {"supercategory": "structural", "color": [193, 0, 92], "id": 138, "name": "net"}, {"supercategory": "textile", "color": [76, 91, 113], "id": 141, "name": "pillow"}, {"supercategory": "ground", "color": [255, 180, 195], "id": 144, "name": "platform"}, {"supercategory": "ground", "color": [106, 154, 176], "id": 145, "name": "playingfield"}, {"supercategory": "ground", "color": [230, 150, 140], "id": 147, "name": "railroad"}, {"supercategory": "water", "color": [60, 143, 255], "id": 148, "name": "river"}, {"supercategory": "ground", "color": [128, 64, 128], "id": 149, "name": "road"}, {"supercategory": "building", "color": [92, 82, 55], "id": 151, "name": "roof"}, {"supercategory": "ground", "color": [254, 212, 124], "id": 154, "name": "sand"}, {"supercategory": "water", "color": [73, 77, 174], "id": 155, "name": "sea"}, {"supercategory": "furniture-stuff", "color": [255, 160, 98], "id": 156, "name": "shelf"}, {"supercategory": "ground", "color": [255, 255, 255], "id": 159, "name": "snow"}, {"supercategory": "furniture-stuff", "color": [104, 84, 109], "id": 161, "name": "stairs"}, {"supercategory": "building", "color": [169, 164, 131], "id": 166, "name": "tent"}, {"supercategory": "textile", "color": [225, 199, 255], "id": 168, "name": "towel"}, {"supercategory": "wall", "color": [137, 54, 74], "id": 171, "name": "wall-brick"}, {"supercategory": "wall", "color": [135, 158, 223], "id": 175, "name": "wall-stone"}, {"supercategory": "wall", "color": [7, 246, 231], "id": 176, "name": "wall-tile"}, {"supercategory": "wall", "color": [107, 255, 200], "id": 177, "name": "wall-wood"}, {"supercategory": "water", "color": [58, 41, 149], "id": 178, "name": "water-other"}, {"supercategory": "window", "color": [183, 121, 142], "id": 180, "name": "window-blind"}, {"supercategory": "window", "color": [255, 73, 97], "id": 181, "name": "window-other"}, {"supercategory": "plant", "color": [107, 142, 35], "id": 184, "name": "tree-merged"}, {"supercategory": "structural", "color": [190, 153, 153], "id": 185, "name": "fence-merged"}, {"supercategory": "ceiling", "color": [146, 139, 141], "id": 186, "name": "ceiling-merged"}, {"supercategory": "sky", "color": [70, 130, 180], "id": 187, "name": "sky-other-merged"}, {"supercategory": "furniture-stuff", "color": [134, 199, 156], "id": 188, "name": "cabinet-merged"}, {"supercategory": "furniture-stuff", "color": [209, 226, 140], "id": 189, "name": "table-merged"}, {"supercategory": "floor", "color": [96, 36, 108], "id": 190, "name": "floor-other-merged"}, {"supercategory": "ground", "color": [96, 96, 96], "id": 191, "name": "pavement-merged"}, {"supercategory": "solid", "color": [64, 170, 64], "id": 192, "name": "mountain-merged"}, {"supercategory": "plant", "color": [152, 251, 152], "id": 193, "name": "grass-merged"}, {"supercategory": "ground", "color": [208, 229, 228], "id": 194, "name": "dirt-merged"}, {"supercategory": "raw-material", "color": [206, 186, 171], "id": 195, "name": "paper-merged"}, {"supercategory": "food-stuff", "color": [152, 161, 64], "id": 196, "name": "food-other-merged"}, {"supercategory": "building", "color": [116, 112, 0], "id": 197, "name": "building-other-merged"}, {"supercategory": "solid", "color": [0, 114, 143], "id": 198, "name": "rock-merged"}, {"supercategory": "wall", "color": [102, 102, 156], "id": 199, "name": "wall-other-merged"}, {"supercategory": "textile", "color": [250, 141, 255], "id": 200, "name": "rug-merged"}]}